[
	{
		"label": "wolves",
		"subentries": [
			{
				"label": "wolf"
			},
			{
				"label": "wolfcorner"
			},
			{
				"label": "wolfindoor"
			},
			{
				"label": "wolfmulti2"
			},
			{
				"label": "wolfswitch"
			},
			{
				"label": "wolfden"
			},
			{
				"label": "wolfden2"
			},
			{
				"label": "wolfmultis",
				"subentries": [
					{
						"label": "wolfmulti"
					},
					{
						"label": "wolfmulti2"
					},
					{
						"label": "wolfmulti5"
					},
					{
						"label": "wolfdenmulti"
					},
					{
						"label": "wolfdenmulti2"
					}
				]
			}
		]
	},
	{
		"label": "chins",
		"subentries": [
			{
				"label": "chinmulti"
			},
			{
				"label": "chin"
			},
			{
				"label": "chin2"
			},
			{
				"label": "chin3"
			}
		]
	},
	{
		"label": "reptiles",
		"subentries": [
			{
				"label": "noodle"
			},
			{
				"label": "patchy"
			},
			{
				"label": "toast"
			},
			{
				"label": "pushpop"
			}
		]
	},
	{
		"label": "insects",
		"subentries": [
			{
				"label": "roaches"
			},
			{
				"label": "hank"
			}
		]
	},
	{
		"label": "crows",
		"subentries": [
			{
				"label": "crowout"
			},
			{
				"label": "crowin"
			},
			{
				"label": "crowmulti"
			},
			{
				"label": "crowmulti2"
			}
		]
	},
	{
		"label": "marmosets",
		"subentries": [
			{
				"label": "marmin"
			},
			{
				"label": "marmout"
			},
			{
				"label": "marmmulti"
			}
		]
	},
	{
		"label": "foxes",
		"subentries": [
			{
				"label": "foxes"
			},
			{
				"label": "foxcorner"
			},
			{
				"label": "foxmulti"
			}
		]
	},
	{
		"label": "parrots"
	},
	{
		"label": "pasture"
	},
	{
		"label": "swap",
		"subentries": [
			{
				"label": "6"
			},
			{
				"label": "5"
			},
			{
				"label": "4"
			},
			{
				"label": "3"
			},
			{
				"label": "2"
			},
			{
				"label": "1"
			}
		]
	},
	{
		"label": "common",
		"subentries": [
			{
				"label": "separator"
			},
			{
				"label": "primary"
			},
			{
				"label": "separator"
			},
			{
				"label": "wolves",
				"import": ["wolves"]
			},
			{
				"label": "chins",
				"import": ["chins"]
			},
			{
				"label": "reptiles",
				"import": ["reptiles"]
			},
			{
				"label": "insects",
				"import": ["insects"]
			},
			{
				"label": "crows",
				"import": ["crows"]
			},
			{
				"label": "marmosets",
				"import": ["marmosets"]
			},
			{
				"label": "foxes",
				"import": ["foxes"]
			},
			{
				"label": "parrots",
				"import": ["parrots"]
			},
			{
				"label": "pasture",
				"import": ["pasture"]
			},
			{
				"label": "separator"
			},
			{
				"label": "swap",
				"import": ["swap"]
			}
		]
	}
]